{
	"miniprogramRoot": "miniprogram/",
	"cloudfunctionRoot": "cloudfunctions/",
	"setting": {
		"urlCheck": true,
		"es6": true,
		"postcss": true,
		"preloadBackgroundData": false,
		"minified": true,
		"newFeature": true,
		"coverView": true,
		"nodeModules": true,
		"autoAudits": false,
		"showShadowRootInWxmlPanel": true,
		"scopeDataCheck": false,
		"checkInvalidKey": true,
		"checkSiteMap": true,
		"uploadWithSourceMap": true,
		"babelSetting": {
			"ignore": [],
			"disablePlugins": [],
			"outputPath": ""
		},
		"useIsolateContext": true,
		"useCompilerModule": true,
		"userConfirmedUseCompilerModuleSwitch": false,
		"packNpmManually": false,
		"packNpmRelationList": []
	},
	"appid": "wx3df45fba6dacd5d3",
	"projectname": "miniprogram-test-1",
	"libVersion": "2.2.5",
	"simulatorType": "wechat",
	"simulatorPluginLibVersion": {},
	"cloudfunctionTemplateRoot": "cloudfunctionTemplate",
	"condition": {
		"search": {
			"current": -1,
			"list": []
		},
		"conversation": {
			"current": -1,
			"list": []
		},
		"plugin": {
			"current": -1,
			"list": []
		},
		"game": {
			"list": []
		},
		"gamePlugin": {
			"current": -1,
			"list": []
		},
		"miniprogram": {
			"current": 0,
			"list": [
				{
					"id": -1,
					"name": "db guide",
					"pathName": "pages/databaseGuide/databaseGuide",
					"query": ""
				},
				{
					"id": -1,
					"name": "pages/list/list",
					"pathName": "pages/list/list",
					"query": "",
					"scene": null
				},
				{
					"id": -1,
					"name": "pages/address/address",
					"pathName": "pages/address/address",
					"query": "",
					"scene": null
				},
				{
					"id": -1,
					"name": "pages/addList/addList",
					"pathName": "pages/addList/addList",
					"scene": null
				}
			]
		}
	}
}